hypothesis_jsonschema_unfit/__init__.py
hypothesis_jsonschema_unfit/_impl.py
hypothesis_jsonschema_unfit-0.1.0.dist-info/WHEEL
hypothesis_jsonschema_unfit-0.1.0.dist-info/METADATA
hypothesis_jsonschema_unfit-0.1.0.dist-info/RECORD
